danatools.py
danatools-0.2.1.dist-info/LICENSE
danatools-0.2.1.dist-info/METADATA
danatools-0.2.1.dist-info/WHEEL
danatools-0.2.1.dist-info/top_level.txt
danatools-0.2.1.dist-info/RECORD
