Metadata-Version: 2.1
Name: danatools
Version: 0.2.1
Summary: A bunch of convenient tools to analyze data
Author-email: Diego Ravignani <diego.ravignani@gmail.com>
License: MIT License
Project-URL: Homepage, https://github.com/ravignad/danatools
Keywords: statistics,data,analysis
Classifier: License :: OSI Approved :: MIT License
Classifier: Programming Language :: Python
Classifier: Programming Language :: Python :: 3
Requires-Python: >=3.8
License-File: LICENSE
Requires-Dist: scipy>=1.9.3
Requires-Dist: matplotlib>=3.7.4
